[{"id":"2c321cce0af18413f91c","on_spotify":true,"publish_date":2020,"archived":false,"genre":{"id":"67f5c962-f972-421b-9975-fac45fcbad21","name":"rock"}},{"id":"18ec3e58c6f51d85bad7","on_spotify":true,"publish_date":2023,"archived":false,"genre":{"id":"7c6038dd-9000-4e7f-ba99-450504c7dea6","name":"cumbia"}},{"id":"8e1d75657a25ede6f3f2","on_spotify":true,"publish_date":2023,"archived":false,"genre":{"id":"5151194d-bfa6-45af-aa46-4e8f81478e2b","name":"Romance"}},{"id":"fd28f0180fb686560074","on_spotify":true,"publish_date":2023,"archived":false,"genre":{"id":"41887381-88ed-41b4-a013-37ff2aabd81f","name":"Romance"}},{"id":"30e2bc97afdca557a524","on_spotify":true,"publish_date":2023,"archived":false,"genre":{"id":"585adf73-2568-44e8-a2f6-958952cac1b2","name":"romance"}}]